iup/__init__.py
iup/config.py
iup/main.py
iup/main_iupd.py
iup_nft-0.6.dist-info/METADATA
iup_nft-0.6.dist-info/WHEEL
iup_nft-0.6.dist-info/entry_points.txt
iup_nft-0.6.dist-info/top_level.txt
iup_nft-0.6.dist-info/RECORD
